{"stats":{"minecraft:mined":{"minecraft:spruce_planks":7,"minecraft:oak_fence":2,"minecraft:spruce_trapdoor":4,"minecraft:jungle_stairs":1,"minecraft:jungle_planks":2,"minecraft:oak_planks":12,"minecraft:oak_wall_sign":1,"minecraft:spruce_stairs":3,"minecraft:seagrass":1,"minecraft:oak_trapdoor":6,"minecraft:dark_oak_slab":6,"minecraft:carrots":26,"minecraft:oak_log":15,"minecraft:potatoes":2,"minecraft:oak_stairs":6,"minecraft:dirt":95,"minecraft:sand":25,"minecraft:bamboo":3,"minecraft:spruce_slab":12},"minecraft:custom":{"minecraft:interact_with_crafting_table":9,"minecraft:open_barrel":3,"minecraft:open_shulker_box":41,"minecraft:leave_game":9,"minecraft:time_since_death":26964,"minecraft:sleep_in_bed":1,"minecraft:climb_one_cm":3910,"minecraft:damage_resisted":92,"minecraft:time_since_rest":17806,"minecraft:sprint_one_cm":170444,"minecraft:open_enderchest":2,"minecraft:damage_taken":1545,"minecraft:walk_one_cm":316960,"minecraft:drop":3,"minecraft:minecart_one_cm":67223,"minecraft:swim_one_cm":3814,"minecraft:talked_to_villager":4,"minecraft:fly_one_cm":271586,"minecraft:open_chest":56,"minecraft:crouch_one_cm":6242,"minecraft:play_time":489845,"minecraft:deaths":3,"minecraft:sneak_time":3378,"minecraft:walk_under_water_one_cm":80137,"minecraft:boat_one_cm":344367,"minecraft:aviate_one_cm":4029438,"minecraft:jump":865,"minecraft:walk_on_water_one_cm":27154,"minecraft:total_world_time":371315,"minecraft:fall_one_cm":20896,"minecraft:horse_one_cm":312},"minecraft:crafted":{"minecraft:oak_door":12,"minecraft:oak_planks":60,"minecraft:wooden_shovel":1,"minecraft:oak_sign":6,"minecraft:crafting_table":2,"minecraft:oak_boat":1,"minecraft:stick":4,"minecraft:chest":2},"minecraft:dropped":{"minecraft:torch":0,"minecraft:oak_sapling":0},"minecraft:killed_by":{"minecraft:zombie":2},"minecraft:used":{"minecraft:oak_fence":2,"minecraft:baked_potato":10,"minecraft:elytra":1,"minecraft:oak_sign":1,"minecraft:chest":2,"minecraft:diamond_axe":73,"minecraft:wooden_shovel":8,"minecraft:oak_door":12,"minecraft:sand":2,"minecraft:dirt":160,"minecraft:crafting_table":2,"minecraft:carrot":34,"minecraft:firework_rocket":53,"minecraft:minecart":1,"minecraft:oak_boat":1},"minecraft:picked_up":{"minecraft:fishing_rod":1,"minecraft:iron_chestplate":1,"minecraft:magma_block":1,"minecraft:tripwire_hook":1,"minecraft:beacon":104,"minecraft:oak_stairs":6,"minecraft:potato":30,"minecraft:birch_planks":19,"minecraft:filled_map":1,"minecraft:oak_log":15,"minecraft:oak_trapdoor":6,"minecraft:dirt":107,"minecraft:elytra":1,"minecraft:iron_leggings":1,"minecraft:experience_bottle":2,"minecraft:oak_sign":1,"minecraft:apple":1,"minecraft:kelp":29,"minecraft:comparator":1,"minecraft:bucket":2,"minecraft:spruce_planks":6,"minecraft:iron_ingot":7,"minecraft:stone_pickaxe":2,"minecraft:iron_nugget":10,"minecraft:bamboo":78,"minecraft:spruce_slab":13,"minecraft:chest":4,"minecraft:birch_sapling":5,"minecraft:oak_planks":12,"minecraft:spruce_trapdoor":4,"minecraft:iron_boots":1,"minecraft:golden_helmet":1,"minecraft:dark_oak_slab":6,"minecraft:chiseled_stone_bricks":1,"minecraft:oak_fence":2,"minecraft:spruce_stairs":6,"minecraft:sand":22,"minecraft:jungle_planks":2,"minecraft:magenta_shulker_box":23,"minecraft:carrot":166,"minecraft:dark_oak_log":7,"minecraft:stone_sword":1,"minecraft:firework_rocket":11,"minecraft:diamond_shovel":1,"minecraft:arrow":3,"minecraft:stone_shovel":1,"minecraft:stone_axe":3,"minecraft:jungle_stairs":1,"minecraft:shears":1,"minecraft:iron_helmet":1,"minecraft:crossbow":1,"minecraft:diamond_axe":1,"minecraft:bread":8,"minecraft:gold_ingot":1,"minecraft:emerald":4,"minecraft:baked_potato":118,"minecraft:oak_sapling":1,"minecraft:coal":13,"minecraft:diamond_pickaxe":3}},"DataVersion":2865}