{"stats":{"minecraft:custom":{"minecraft:animals_bred":22,"minecraft:interact_with_crafting_table":419,"minecraft:open_barrel":46,"minecraft:open_shulker_box":1222,"minecraft:bell_ring":21,"minecraft:leave_game":95,"minecraft:time_since_death":14532,"minecraft:damage_resisted":215,"minecraft:sprint_one_cm":6317499,"minecraft:damage_blocked_by_shield":3480,"minecraft:drop":715,"minecraft:talked_to_villager":49,"minecraft:deaths":75,"minecraft:jump":34827,"minecraft:interact_with_brewingstand":193,"minecraft:walk_on_water_one_cm":595212,"minecraft:enchant_item":52,"minecraft:interact_with_furnace":466,"minecraft:traded_with_villager":53,"minecraft:interact_with_cartography_table":1,"minecraft:play_one_minute":4567106,"minecraft:sleep_in_bed":24,"minecraft:open_enderchest":290,"minecraft:damage_dealt":60106,"minecraft:crouch_one_cm":73535,"minecraft:interact_with_smoker":5,"minecraft:use_cauldron":111,"minecraft:inspect_dispenser":85,"minecraft:horse_one_cm":830504,"minecraft:inspect_dropper":2,"minecraft:interact_with_anvil":20,"minecraft:mob_kills":4362,"minecraft:inspect_hopper":83,"minecraft:fill_cauldron":37,"minecraft:climb_one_cm":132160,"minecraft:walk_one_cm":13527248,"minecraft:sneak_time":55773,"minecraft:walk_under_water_one_cm":705417,"minecraft:boat_one_cm":5021182,"minecraft:interact_with_blast_furnace":2,"minecraft:interact_with_grindstone":3,"minecraft:interact_with_stonecutter":4,"minecraft:time_since_rest":14552,"minecraft:damage_taken":44153,"minecraft:trigger_trapped_chest":14,"minecraft:minecart_one_cm":757825,"minecraft:swim_one_cm":1401,"minecraft:fly_one_cm":4309648,"minecraft:open_chest":4377,"minecraft:aviate_one_cm":28201762,"minecraft:fish_caught":21,"minecraft:fall_one_cm":563263},"minecraft:killed":{"minecraft:spider":32,"minecraft:skeleton":34,"minecraft:chicken":30,"minecraft:silverfish":1,"minecraft:skeleton_horse":1,"minecraft:magma_cube":35,"minecraft:parrot":3,"minecraft:creeper":22,"minecraft:sheep":1,"minecraft:zombie":70,"minecraft:ghast":3,"minecraft:blaze":84,"minecraft:zombie_pigman":294,"minecraft:slime":8,"minecraft:phantom":11,"minecraft:drowned":6,"minecraft:ocelot":1,"minecraft:husk":2,"minecraft:rabbit":1,"minecraft:bat":1,"minecraft:wither_skeleton":3,"minecraft:enderman":3698},"minecraft:used":{"minecraft:dispenser":19,"minecraft:ladder":118,"minecraft:chest":89,"minecraft:nether_wart":177,"minecraft:stone":279,"minecraft:iron_sword":668,"minecraft:white_shulker_box":4,"minecraft:soul_sand":183,"minecraft:nether_bricks":32,"minecraft:acacia_sapling":4,"minecraft:snowball":2599,"minecraft:obsidian":124,"minecraft:glass":677,"minecraft:spruce_boat":5,"minecraft:packed_ice":733,"minecraft:grass_block":3,"minecraft:lava_bucket":14,"minecraft:orange_shulker_box":122,"minecraft:stone_brick_stairs":19,"minecraft:stone_bricks":27,"minecraft:repeater":37,"minecraft:bow":778,"minecraft:snow":36,"minecraft:dark_oak_boat":10,"minecraft:gray_bed":6,"minecraft:jungle_button":1,"minecraft:oak_sapling":1,"minecraft:blue_shulker_box":3,"minecraft:furnace":27,"minecraft:cooked_cod":368,"minecraft:beetroot_seeds":4,"minecraft:egg":89,"minecraft:potato":108,"minecraft:end_rod":1,"minecraft:diorite":4,"minecraft:end_stone_bricks":1,"minecraft:chorus_fruit":115,"minecraft:stone_pickaxe":5145,"minecraft:cactus":31,"minecraft:ender_pearl":42,"minecraft:wooden_pickaxe":59,"minecraft:sandstone":68,"minecraft:jungle_pressure_plate":2,"minecraft:diamond_axe":419,"minecraft:sugar_cane":97,"minecraft:jungle_boat":20,"minecraft:golden_apple":3,"minecraft:dark_oak_trapdoor":7,"minecraft:sand":1269,"minecraft:mushroom_stew":5,"minecraft:crossbow":28,"minecraft:end_stone":61,"minecraft:redstone_torch":297,"minecraft:lever":2,"minecraft:firework_rocket":41,"minecraft:string":1,"minecraft:brown_wool":1,"minecraft:bread":52,"minecraft:stone_button":11,"minecraft:melon_slice":2,"minecraft:iron_door":14,"minecraft:gravel":266,"minecraft:diamond_sword":1087,"minecraft:andesite":1,"minecraft:oak_boat":1,"minecraft:experience_bottle":3,"minecraft:oak_fence":1,"minecraft:purpur_block":151,"minecraft:stone_sword":1692,"minecraft:acacia_log":79,"minecraft:flint_and_steel":181,"minecraft:carved_pumpkin":3,"minecraft:stone_shovel":2868,"minecraft:dried_kelp":394,"minecraft:redstone":125,"minecraft:ender_chest":4,"minecraft:netherrack":1534,"minecraft:torch":178,"minecraft:brewing_stand":10,"minecraft:dirt":474,"minecraft:anvil":2,"minecraft:chorus_flower":64,"minecraft:hopper":16,"minecraft:shulker_box":25,"minecraft:jungle_trapdoor":2,"minecraft:granite":11,"minecraft:iron_hoe":3,"minecraft:red_shulker_box":1,"minecraft:stone_brick_slab":153,"minecraft:smooth_sandstone":1,"minecraft:jungle_log":1,"minecraft:glowstone":32,"minecraft:trapped_chest":1,"minecraft:stone_pressure_plate":6,"minecraft:acacia_boat":4,"minecraft:wheat_seeds":156,"minecraft:water_bucket":72,"minecraft:iron_ore":22,"minecraft:cobblestone_stairs":20,"minecraft:snow_block":83,"minecraft:yellow_shulker_box":2,"minecraft:baked_potato":7,"minecraft:red_mushroom_block":4,"minecraft:cauldron":2,"minecraft:cobblestone_slab":5,"minecraft:salmon":3,"minecraft:tnt":61,"minecraft:crafting_table":21,"minecraft:cod":7,"minecraft:lime_shulker_box":2,"minecraft:piston":41,"minecraft:diamond_pickaxe":9551,"minecraft:diamond_shovel":5926,"minecraft:chicken":1,"minecraft:iron_pickaxe":958,"minecraft:stone_slab":5,"minecraft:stone_axe":243,"minecraft:fishing_rod":41,"minecraft:cobblestone":1626,"minecraft:potion":23,"minecraft:bucket":168,"minecraft:lapis_block":1,"minecraft:splash_potion":30,"minecraft:kelp":4},"minecraft:mined":{"minecraft:red_shulker_box":1,"minecraft:stone_pressure_plate":2,"minecraft:oak_sapling":1,"minecraft:farmland":18,"minecraft:jungle_leaves":204,"minecraft:brewing_stand":3,"minecraft:obsidian":152,"minecraft:carved_pumpkin":3,"minecraft:spruce_trapdoor":1,"minecraft:granite":214,"minecraft:acacia_log":110,"minecraft:grass_block":204,"minecraft:jungle_log":355,"minecraft:oak_pressure_plate":1,"minecraft:hopper":17,"minecraft:nether_wart":34,"minecraft:spawner":1,"minecraft:chorus_flower":90,"minecraft:magma_block":179,"minecraft:glowstone":97,"minecraft:dark_oak_trapdoor":16,"minecraft:iron_ore":476,"minecraft:pumpkin":9,"minecraft:anvil":1,"minecraft:white_shulker_box":3,"minecraft:jungle_pressure_plate":2,"minecraft:end_stone_bricks":9,"minecraft:spruce_slab":1,"minecraft:tripwire":1,"minecraft:jungle_trapdoor":2,"minecraft:jungle_button":1,"minecraft:cut_sandstone":6,"minecraft:brown_mushroom":36,"minecraft:kelp_plant":47,"minecraft:purpur_stairs":1,"minecraft:clay":28,"minecraft:torch":55,"minecraft:melon":20,"minecraft:poppy":6,"minecraft:chest":56,"minecraft:dead_bush":2,"minecraft:mushroom_stem":12,"minecraft:glass":483,"minecraft:nether_quartz_ore":21,"minecraft:cobblestone":441,"minecraft:lime_shulker_box":3,"minecraft:sugar_cane":364,"minecraft:wall_torch":34,"minecraft:cauldron":1,"minecraft:seagrass":4,"minecraft:repeater":24,"minecraft:lapis_block":1,"minecraft:wheat":175,"minecraft:tnt":7,"minecraft:purpur_block":48,"minecraft:stone_brick_stairs":3,"minecraft:grass":338,"minecraft:oak_log":21,"minecraft:beetroots":6,"minecraft:sand":3108,"minecraft:dirt":625,"minecraft:blue_shulker_box":3,"minecraft:red_mushroom_block":94,"minecraft:dispenser":18,"minecraft:netherrack":2484,"minecraft:piston":41,"minecraft:oak_leaves":166,"minecraft:diamond_ore":82,"minecraft:end_stone":226,"minecraft:shulker_box":25,"minecraft:nether_bricks":491,"minecraft:lever":2,"minecraft:ladder":62,"minecraft:stone_button":7,"minecraft:spruce_fence":4,"minecraft:orange_shulker_box":116,"minecraft:redstone_wire":91,"minecraft:spruce_leaves":1,"minecraft:acacia_slab":3,"minecraft:kelp":17,"minecraft:red_mushroom":45,"minecraft:sandstone":1927,"minecraft:redstone_ore":110,"minecraft:furnace":28,"minecraft:snow":4096,"minecraft:andesite":170,"minecraft:nether_brick_fence":22,"minecraft:potatoes":48,"minecraft:cobblestone_slab":4,"minecraft:vine":64,"minecraft:packed_ice":3164,"minecraft:chorus_plant":62,"minecraft:bamboo":9,"minecraft:stone":3603,"minecraft:yellow_shulker_box":2,"minecraft:cake":1,"minecraft:ender_chest":2,"minecraft:redstone_wall_torch":20,"minecraft:acacia_leaves":11,"minecraft:soul_sand":458,"minecraft:snow_block":240,"minecraft:stone_brick_slab":41,"minecraft:dandelion":15,"minecraft:oak_fence":8,"minecraft:crafting_table":16,"minecraft:purpur_pillar":2,"minecraft:lapis_ore":21,"minecraft:diorite":229,"minecraft:cactus":22,"minecraft:redstone_torch":266,"minecraft:ice":24,"minecraft:gray_bed":6,"minecraft:grass_path":7,"minecraft:coal_ore":240,"minecraft:end_rod":1,"minecraft:gravel":498,"minecraft:stone_bricks":433,"minecraft:gold_ore":57,"minecraft:fern":5},"minecraft:crafted":{"minecraft:ender_chest":5,"minecraft:jungle_button":1,"minecraft:oak_planks":40,"minecraft:cobblestone_slab":6,"minecraft:melon":10,"minecraft:blaze_powder":60,"minecraft:cobblestone_stairs":24,"minecraft:stone":47,"minecraft:snow":6,"minecraft:diamond_shovel":3,"minecraft:lever":1,"minecraft:nether_brick":18,"minecraft:cooked_mutton":1,"minecraft:glass":1122,"minecraft:repeater":7,"minecraft:hopper":5,"minecraft:bow":4,"minecraft:stone_brick_slab":174,"minecraft:diamond_helmet":2,"minecraft:diamond_leggings":3,"minecraft:iron_boots":4,"minecraft:stone_pressure_plate":3,"minecraft:chest":41,"minecraft:iron_door":6,"minecraft:ender_eye":5,"minecraft:white_shulker_box":6,"minecraft:glass_bottle":96,"minecraft:emerald":56,"minecraft:arrow":28,"minecraft:cauldron":1,"minecraft:crafting_table":7,"minecraft:jungle_boat":4,"minecraft:wooden_pickaxe":1,"minecraft:iron_helmet":10,"minecraft:jungle_pressure_plate":2,"minecraft:nether_brick_fence":54,"minecraft:brewing_stand":7,"minecraft:dispenser":4,"minecraft:tnt":27,"minecraft:stone_brick_stairs":20,"minecraft:charcoal":6,"minecraft:diamond_pickaxe":4,"minecraft:book":32,"minecraft:iron_chestplate":4,"minecraft:yellow_dye":2,"minecraft:paper":513,"minecraft:shield":6,"minecraft:stick":978,"minecraft:stone_slab":18,"minecraft:iron_ingot":939,"minecraft:iron_pickaxe":9,"minecraft:iron_block":92,"minecraft:stone_sword":30,"minecraft:snow_block":102,"minecraft:gold_ingot":72,"minecraft:redstone_torch":15,"minecraft:packed_ice":1,"minecraft:stone_shovel":58,"minecraft:fishing_rod":3,"minecraft:tripwire_hook":6,"minecraft:popped_chorus_fruit":1,"minecraft:furnace":3,"minecraft:stone_button":2,"minecraft:piston":4,"minecraft:jungle_trapdoor":2,"minecraft:blue_shulker_box":1,"minecraft:bone_meal":6,"minecraft:diamond_block":9,"minecraft:flint_and_steel":5,"minecraft:diamond":153,"minecraft:yellow_shulker_box":2,"minecraft:ladder":231,"minecraft:slime_ball":18,"minecraft:red_shulker_box":1,"minecraft:stone_pickaxe":62,"minecraft:diamond_boots":6,"minecraft:spruce_boat":2,"minecraft:glistering_melon_slice":15,"minecraft:magma_cream":10,"minecraft:sugar":50,"minecraft:red_dye":1,"minecraft:cooked_cod":1153,"minecraft:crossbow":5,"minecraft:diamond_sword":3,"minecraft:dried_kelp":441,"minecraft:iron_sword":10,"minecraft:smooth_sandstone":2,"minecraft:bucket":20,"minecraft:stone_axe":3,"minecraft:glowstone":32,"minecraft:enchanted_book":1,"minecraft:acacia_boat":1,"minecraft:bread":46,"minecraft:air":0,"minecraft:jungle_planks":688,"minecraft:blue_dye":9,"minecraft:golden_apple":6,"minecraft:white_dye":6,"minecraft:fermented_spider_eye":4,"minecraft:iron_leggings":4,"minecraft:anvil":1,"minecraft:acacia_planks":160,"minecraft:torch":224,"minecraft:clay":28,"minecraft:lapis_lazuli":765,"minecraft:lapis_block":16,"minecraft:firework_rocket":714,"minecraft:trapped_chest":1,"minecraft:diamond_chestplate":3},"minecraft:picked_up":{"minecraft:iron_chestplate":5,"minecraft:wheat":200,"minecraft:flower_pot":2,"minecraft:nether_brick_fence":100,"minecraft:anvil":1,"minecraft:lead":15,"minecraft:stone_slab":129,"minecraft:diamond_sword":6,"minecraft:oak_stairs":6,"minecraft:potion":15,"minecraft:stone_brick_stairs":5,"minecraft:brewing_stand":3,"minecraft:golden_sword":19,"minecraft:lapis_block":1,"minecraft:dark_oak_trapdoor":24,"minecraft:string":115,"minecraft:iron_leggings":5,"minecraft:pufferfish":5,"minecraft:beetroot":4,"minecraft:sea_pickle":2,"minecraft:diamond_leggings":5,"minecraft:gold_nugget":137,"minecraft:bucket":28,"minecraft:spruce_planks":4,"minecraft:redstone_torch":308,"minecraft:cobblestone_slab":10,"minecraft:iron_pickaxe":5,"minecraft:melon_slice":118,"minecraft:furnace":28,"minecraft:iron_boots":5,"minecraft:white_glazed_terracotta":4,"minecraft:stick":112,"minecraft:orange_shulker_box":133,"minecraft:composter":1,"minecraft:oak_fence":8,"minecraft:torch":311,"minecraft:acacia_log":104,"minecraft:purpur_pillar":2,"minecraft:spruce_stairs":72,"minecraft:snow_block":130,"minecraft:dried_kelp":150,"minecraft:diorite":233,"minecraft:cauldron":1,"minecraft:stone_sword":17,"minecraft:cactus":46,"minecraft:rotten_flesh":400,"minecraft:tropical_fish":4,"minecraft:carved_pumpkin":3,"minecraft:iron_block":448,"minecraft:end_rod":1,"minecraft:chorus_flower":96,"minecraft:blaze_rod":43,"minecraft:obsidian":177,"minecraft:cod":206,"minecraft:snowball":6707,"minecraft:blaze_powder":8,"minecraft:cobblestone":4279,"minecraft:magma_block":263,"minecraft:cooked_beef":112,"minecraft:feather":80,"minecraft:jungle_pressure_plate":2,"minecraft:magma_cream":9,"minecraft:repeater":36,"minecraft:andesite":231,"minecraft:iron_door":13,"minecraft:water_bucket":5,"minecraft:jungle_log":464,"minecraft:brown_wool":1,"minecraft:dark_oak_boat":11,"minecraft:beacon":6,"minecraft:potato":539,"minecraft:flint":84,"minecraft:acacia_boat":4,"minecraft:lapis_lazuli":335,"minecraft:dirt":932,"minecraft:leather_boots":3,"minecraft:glass":790,"minecraft:bone":91,"minecraft:bow":8,"minecraft:wheat_seeds":735,"minecraft:bell":1,"minecraft:mossy_stone_bricks":1,"minecraft:diamond_helmet":5,"minecraft:rabbit":5,"minecraft:glowstone_dust":282,"minecraft:bamboo":165,"minecraft:oak_planks":37,"minecraft:stone_hoe":1,"minecraft:ghast_tear":1,"minecraft:oak_pressure_plate":2,"minecraft:poisonous_potato":6,"minecraft:jungle_planks":50,"minecraft:sand":3366,"minecraft:melon":4,"minecraft:ink_sac":6,"minecraft:grass_block":196,"minecraft:jungle_slab":151,"minecraft:shulker_box":28,"minecraft:jungle_leaves":47,"minecraft:iron_hoe":1,"minecraft:dispenser":29,"minecraft:diamond":99,"minecraft:spruce_boat":10,"minecraft:lever":3,"minecraft:crossbow":2,"minecraft:granite":235,"minecraft:white_concrete":7,"minecraft:bread":37,"minecraft:oak_sapling":30,"minecraft:netherrack":3433,"minecraft:chorus_fruit":350,"minecraft:oak_leaves":78,"minecraft:diamond_pickaxe":13,"minecraft:end_stone_bricks":9,"minecraft:fishing_rod":7,"minecraft:crafting_table":15,"minecraft:sandstone_slab":19,"minecraft:nether_wart":194,"minecraft:chicken":4,"minecraft:ladder":251,"minecraft:clay_ball":112,"minecraft:brown_mushroom":36,"minecraft:packed_ice":4061,"minecraft:wooden_pickaxe":2,"minecraft:purpur_block":45,"minecraft:shield":7,"minecraft:jungle_trapdoor":4,"minecraft:elytra":7,"minecraft:snow":30,"minecraft:flint_and_steel":5,"minecraft:compass":1,"minecraft:oak_boat":3,"minecraft:jungle_sapling":23,"minecraft:poppy":10,"minecraft:spruce_slab":1,"minecraft:blue_shulker_box":3,"minecraft:sugar_cane":697,"minecraft:chest":59,"minecraft:piston":46,"minecraft:spruce_trapdoor":1,"minecraft:phantom_membrane":15,"minecraft:diamond_hoe":1,"minecraft:egg":9,"minecraft:lime_shulker_box":12,"minecraft:sandstone":1655,"minecraft:end_stone":255,"minecraft:stone":665,"minecraft:bowl":2,"minecraft:spruce_fence":4,"minecraft:stone_button":10,"minecraft:carrot":2,"minecraft:redstone":1203,"minecraft:mushroom_stem":10,"minecraft:stone_pressure_plate":4,"minecraft:smooth_sandstone_slab":2,"minecraft:tnt":7,"minecraft:red_shulker_box":1,"minecraft:arrow":129,"minecraft:stone_shovel":23,"minecraft:diamond_chestplate":5,"minecraft:cooked_cod":589,"minecraft:beetroot_seeds":12,"minecraft:nether_bricks":711,"minecraft:shears":3,"minecraft:diamond_boots":2,"minecraft:hay_block":19,"minecraft:saddle":1,"minecraft:gold_ingot":8,"minecraft:white_shulker_box":3,"minecraft:mutton":2,"minecraft:lapis_ore":3,"minecraft:lime_bed":1,"minecraft:yellow_shulker_box":2,"minecraft:jungle_boat":23,"minecraft:golden_carrot":24,"minecraft:tripwire_hook":4,"minecraft:salmon":14,"minecraft:leather":63,"minecraft:cut_sandstone":16,"minecraft:red_mushroom_block":158,"minecraft:red_mushroom":48,"minecraft:filled_map":1,"minecraft:ice":18,"minecraft:mushroom_stew":3,"minecraft:purpur_stairs":1,"minecraft:oak_log":21,"minecraft:lily_pad":2,"minecraft:jungle_button":2,"minecraft:gunpowder":94,"minecraft:cobblestone_wall":38,"minecraft:paper":182,"minecraft:smooth_sandstone":15,"minecraft:apple":1,"minecraft:stone_bricks":465,"minecraft:kelp":284,"minecraft:rabbit_hide":4,"minecraft:iron_ingot":173,"minecraft:stone_pickaxe":45,"minecraft:iron_ore":569,"minecraft:glass_bottle":20,"minecraft:gray_bed":6,"minecraft:iron_sword":8,"minecraft:acacia_sapling":13,"minecraft:soul_sand":562,"minecraft:book":1,"minecraft:oak_slab":10,"minecraft:dark_oak_slab":2,"minecraft:pumpkin":9,"minecraft:stone_brick_slab":38,"minecraft:quartz":46,"minecraft:dandelion":30,"minecraft:gravel":526,"minecraft:lava_bucket":7,"minecraft:gold_ore":57,"minecraft:spider_eye":31,"minecraft:spruce_door":1,"minecraft:firework_rocket":260,"minecraft:diamond_shovel":3,"minecraft:pumpkin_seeds":10,"minecraft:coal_ore":3,"minecraft:slime_ball":23,"minecraft:stone_axe":12,"minecraft:iron_helmet":6,"minecraft:diamond_axe":7,"minecraft:gray_wool":2,"minecraft:baked_potato":12,"minecraft:acacia_slab":5,"minecraft:melon_seeds":1,"minecraft:coal":706,"minecraft:hopper":20,"minecraft:ender_pearl":916},"minecraft:killed_by":{"minecraft:ghast":2,"minecraft:wither_skeleton":5,"minecraft:creeper":6,"minecraft:magma_cube":1,"minecraft:blaze":10,"minecraft:zombie":3,"minecraft:zombie_pigman":1,"minecraft:enderman":2,"minecraft:skeleton":6},"minecraft:broken":{"minecraft:stone_pickaxe":33,"minecraft:diamond_shovel":1,"minecraft:stone_axe":1,"minecraft:stone_shovel":19,"minecraft:stone_sword":10,"minecraft:flint_and_steel":1,"minecraft:wooden_pickaxe":1,"minecraft:iron_pickaxe":1},"minecraft:dropped":{"minecraft:iron_sword":3,"minecraft:diamond_axe":1,"minecraft:oak_log":5,"minecraft:ender_pearl":331,"minecraft:lime_shulker_box":9,"minecraft:crossbow":1,"minecraft:jungle_planks":2,"minecraft:elytra":3,"minecraft:cod":13,"minecraft:melon":6,"minecraft:dirt":69,"minecraft:dispenser":1,"minecraft:cooked_cod":52,"minecraft:snowball":68,"minecraft:jungle_sapling":3,"minecraft:phantom_membrane":1,"minecraft:sand":3,"minecraft:iron_pickaxe":3,"minecraft:fishing_rod":2,"minecraft:bone":2,"minecraft:stone_axe":2,"minecraft:gravel":28,"minecraft:sugar_cane":2,"minecraft:wheat":14,"minecraft:obsidian":3,"minecraft:beetroot":4,"minecraft:rotten_flesh":130,"minecraft:oak_planks":26,"minecraft:diamond_shovel":1,"minecraft:salmon":3,"minecraft:coal_ore":1,"minecraft:ladder":1,"minecraft:beetroot_seeds":8,"minecraft:chest":1,"minecraft:hopper":2,"minecraft:arrow":43,"minecraft:glass":6,"minecraft:stone_brick_stairs":6,"minecraft:netherrack":1,"minecraft:firework_rocket":168,"minecraft:stone_hoe":1,"minecraft:water_bucket":7,"minecraft:orange_shulker_box":1,"minecraft:oak_slab":10,"minecraft:wheat_seeds":2,"minecraft:lead":2,"minecraft:cobblestone":2,"minecraft:iron_helmet":1,"minecraft:pufferfish":1,"minecraft:mushroom_stew":2,"minecraft:grass_block":38,"minecraft:stick":6,"minecraft:golden_carrot":20,"minecraft:torch":1,"minecraft:white_concrete":7,"minecraft:melon_slice":1,"minecraft:iron_door":1,"minecraft:jungle_leaves":9,"minecraft:dried_kelp":49,"minecraft:oak_stairs":6,"minecraft:jungle_boat":2,"minecraft:paper":158,"minecraft:string":14,"minecraft:bucket":3,"minecraft:stone_brick_slab":57,"minecraft:redstone":64,"minecraft:ender_chest":1,"minecraft:stone_sword":4,"minecraft:blaze_rod":10,"minecraft:bowl":1,"minecraft:stone_shovel":3,"minecraft:nether_bricks":64,"minecraft:shulker_box":1,"minecraft:flint_and_steel":1,"minecraft:filled_map":1,"minecraft:diamond_sword":4,"minecraft:spruce_boat":2,"minecraft:stone":2,"minecraft:diamond_pickaxe":9,"minecraft:oak_sapling":12,"minecraft:stone_bricks":162,"minecraft:diamond_boots":1,"minecraft:sandstone":64,"minecraft:bow":2,"minecraft:stone_pickaxe":3}},"DataVersion":2230}